pydecon/__init__.py
pydecon/_version.py
pydecon/clean.py
pydecon/decon.py
pydecon/utils.py
tests/__init__.py
tests/test_utils.py
pydecon-0.0.1.dist-info/LICENSE.md
pydecon-0.0.1.dist-info/METADATA
pydecon-0.0.1.dist-info/WHEEL
pydecon-0.0.1.dist-info/top_level.txt
pydecon-0.0.1.dist-info/RECORD
