Metadata-Version: 2.1
Name: pydecon
Version: 0.0.1
Summary: A python library for deconvolving image data
Home-page: https://github.com/david-hoffman/pyDecon
Author: David Hoffman
Author-email: dave.p.hoffman@gmail.com
License: Apache V2.0
Platform: UNKNOWN
Classifier: Development Status :: 3 - Alpha
Classifier: Programming Language :: Python :: 3
Classifier: License :: OSI Approved :: Apache Software License
Classifier: Natural Language :: English
Classifier: Operating System :: OS Independent
Classifier: Topic :: Scientific/Engineering
Requires-Python: >=3.8
Requires-Dist: numpy
Requires-Dist: scipy
Requires-Dist: tqdm
